jlop/__init__.py
jlop/colors.py
jlop/fonts/BaKoMa/cmr10.ttf
jlop/fonts/Hershey-Noialles/Hershey-Noailles-Times-Simplex-Light.ttf
jlop/fonts/KulimPark/KulimPark-Regular.ttf
jlop/fonts/Pecita/Pecita.otf
jlop/fonts/TexGyreHero/texgyreheros-regular.otf
jlop/load_style.py
jlop/ratios.py
jlop/styles/classic.mplstyle
jlop/styles/default.mplstyle
jlop/styles/modern.mplstyle
jlop/styles/retro.mplstyle
jlop/templates/__init__.py
jlop/templates/cross_style_plots.py
jlop-0.0.4.dist-info/LICENSE
jlop-0.0.4.dist-info/METADATA
jlop-0.0.4.dist-info/WHEEL
jlop-0.0.4.dist-info/RECORD
